clikr_kit/__init__.py
clikr_kit-0.1.0.dist-info/METADATA
clikr_kit-0.1.0.dist-info/WHEEL
clikr_kit-0.1.0.dist-info/RECORD
