Metadata-Version: 2.3
Name: clikr-kit
Version: 0.1.0
Summary: 
Author: Olivier Corbeil
Author-email: olicorb2000@gmail.com
Requires-Python: >=3.12
Classifier: Programming Language :: Python :: 3
Classifier: Programming Language :: Python :: 3.12
Classifier: Programming Language :: Python :: 3.13
